hadamard_transform/__init__.py
hadamard_transform-0.1.3.dist-info/LICENSE
hadamard_transform-0.1.3.dist-info/METADATA
hadamard_transform-0.1.3.dist-info/WHEEL
hadamard_transform-0.1.3.dist-info/top_level.txt
hadamard_transform-0.1.3.dist-info/RECORD
