Metadata-Version: 2.1
Name: hadamard-transform
Version: 0.1.3
Summary: Fast Walsh–Hadamard Transform (FWHT) in PyTorch
Home-page: https://github.com/amitport/hadamard-transform
Author: Amit Portnoy
Author-email: amit.portnoy@gmail.com
Project-URL: Issues, https://github.com/amitport/hadamard-transform/issues
Project-URL: Changelog, https://github.com/amitport/hadamard-transform/releases
Classifier: Programming Language :: Python :: 3
Classifier: License :: OSI Approved :: MIT License
Classifier: Operating System :: OS Independent
Requires-Python: >=3.9
License-File: LICENSE
Requires-Dist: torch (>=1.10)
Provides-Extra: test
Requires-Dist: pytest ; extra == 'test'
